{
  "title": "Project Details",
  "type": "object",
  "required": ["name", "url", "crawlOpts", "scenarioOpts"],
  "properties": {
    "name": {
      "type": "string",
      "title": "Name",
      "minLength": 1
    },
    "description": {
      "type": "string",
      "title": "Description",
      "default": ""
    },
    "url": {
      "type": "string",
      "title": "Start URL",
      "format": "uri"
    },

    "crawlOpts": {
      "title": "Crawl Options",
      "type": "object",
      "required": ["maxDepth", "maxResources", "delay"],
      "properties": {
        "maxDepth": {
          "type": "number",
          "title": "Maximum crawl depth",
          "description": "Start URL has depth 0. All resources linked from it have depth 1 and so on.",
          "default": -1,
          "ui": {
            "step": 1
          }
        },
        "maxResources": {
          "type": "number",
          "title": "Maximum resources",
          "description": "Maximum number of resources to be crawled per each individual site.",
          "default": 100,
          "ui": {
            "step": 1
          }
        },
        "delay": {
          "type": "number",
          "title": "Crawl delay",
          "description": "Delay in miliseconds between fetching two consecutive resources.",
          "default": 1000,
          "ui": {
            "step": 1
          }
        },
        "hostnameRe": {
          "type": "string",
          "title": "Domain regexp filter",
          "description": "Based on URL hostname, filter which html pages should be queued for scraping. Leave empty to only add resources from the same domain (including subdomains). Ex: /\\.org$/ only links from .org domains will be scraped.",
          "default": ""
        },
        "pathnameRe": {
          "type": "string",
          "title": "Pathname regexp filter",
          "description": "Based on URL pathname, filter which html pages should be queued for scraping. Leave empty to add all links. Ex: /product/ - only links like extra-product-extra.html will be scraped. Ex: /category\\/product/ - only links like extra-category/product-extra.html will be scraped.",
          "default": ""
        }
      }
    },

    "scenarioOpts": {
      "type": "object",
      "title": "Scrape Scenario Options",
      "required": ["name"],
      "properties": {
        "name": {
          "type": "string",
          "title": "Scrape Scenario"
        },
        "description": {
          "type": "string",
          "ui": {
            "customField": "ScenarioDescription"
          }
        },
        "homepage": {
          "type": "string",
          "format": "uri",
          "ui": {
            "customField": "ScenarioLink"
          }
        }
      }
    }
  }
}